deduplipy/__init__.py
deduplipy/config.py
deduplipy/datasets.py
deduplipy/active_learning/__init__.py
deduplipy/active_learning/active_learning.py
deduplipy/active_learning/utils_active_learning.py
deduplipy/blocking/__init__.py
deduplipy/blocking/blocking.py
deduplipy/blocking/blocking_rules.py
deduplipy/blocking/set_cover.py
deduplipy/classifier_pipeline/__init__.py
deduplipy/classifier_pipeline/classifier_pipeline.py
deduplipy/clustering/__init__.py
deduplipy/clustering/clustering.py
deduplipy/clustering/fill_missing_edges.py
deduplipy/data/stoxx50_extended_with_id.xlsx
deduplipy/data/voter_names.csv
deduplipy/data/voter_names_17k.csv
deduplipy/data/voter_names_35k.csv
deduplipy/data/voter_names_80k.csv
deduplipy/deduplicator/__init__.py
deduplipy/deduplicator/deduplicator.py
deduplipy/sampling/__init__.py
deduplipy/sampling/minhash_sampling.py
deduplipy/sampling/naive_sampling.py
deduplipy/sampling/sampler.py
deduplipy/string_metrics/__init__.py
deduplipy/string_metrics/string_metrics.py
DedupliPy-0.8.dist-info/LICENSE
DedupliPy-0.8.dist-info/METADATA
DedupliPy-0.8.dist-info/WHEEL
DedupliPy-0.8.dist-info/top_level.txt
DedupliPy-0.8.dist-info/RECORD
