Metadata-Version: 2.1
Name: DedupliPy
Version: 0.8
Summary: End-to-end deduplication solution
Home-page: https://github.com/fritshermans/deduplipy
Author: Frits Hermans
Classifier: Programming Language :: Python :: 3
Classifier: License :: OSI Approved :: MIT License
Classifier: Operating System :: OS Independent
Requires-Python: >=3.6.9
License-File: LICENSE
Requires-Dist: pandas
Requires-Dist: numpy
Requires-Dist: scipy
Requires-Dist: scikit-learn
Requires-Dist: networkx
Requires-Dist: python-Levenshtein
Requires-Dist: thefuzz
Requires-Dist: modAL-python
Requires-Dist: openpyxl
Requires-Dist: pytest
Requires-Dist: fancyimpute
Requires-Dist: pyminhash
Provides-Extra: base
Requires-Dist: pandas ; extra == 'base'
Requires-Dist: numpy ; extra == 'base'
Requires-Dist: scipy ; extra == 'base'
Requires-Dist: scikit-learn ; extra == 'base'
Requires-Dist: networkx ; extra == 'base'
Requires-Dist: python-Levenshtein ; extra == 'base'
Requires-Dist: thefuzz ; extra == 'base'
Requires-Dist: modAL-python ; extra == 'base'
Requires-Dist: openpyxl ; extra == 'base'
Requires-Dist: pytest ; extra == 'base'
Requires-Dist: fancyimpute ; extra == 'base'
Requires-Dist: pyminhash ; extra == 'base'
Provides-Extra: dev
Requires-Dist: pandas ; extra == 'dev'
Requires-Dist: numpy ; extra == 'dev'
Requires-Dist: scipy ; extra == 'dev'
Requires-Dist: scikit-learn ; extra == 'dev'
Requires-Dist: networkx ; extra == 'dev'
Requires-Dist: python-Levenshtein ; extra == 'dev'
Requires-Dist: thefuzz ; extra == 'dev'
Requires-Dist: modAL-python ; extra == 'dev'
Requires-Dist: openpyxl ; extra == 'dev'
Requires-Dist: pytest ; extra == 'dev'
Requires-Dist: fancyimpute ; extra == 'dev'
Requires-Dist: pyminhash ; extra == 'dev'
Requires-Dist: matplotlib ; extra == 'dev'
Requires-Dist: jupyterlab ; extra == 'dev'
Requires-Dist: sphinx (==3.5.4) ; extra == 'dev'
Requires-Dist: nbsphinx ; extra == 'dev'
Requires-Dist: sphinx-rtd-theme ; extra == 'dev'
Provides-Extra: docs
Requires-Dist: sphinx (==3.5.4) ; extra == 'docs'
Requires-Dist: nbsphinx ; extra == 'docs'
Requires-Dist: sphinx-rtd-theme ; extra == 'docs'
